poliduckie_segmentation/__init__.py
poliduckie_segmentation/control.py
poliduckie_segmentation/line_extraction.py
poliduckie_segmentation/model.py
poliduckie_segmentation/pre_processing.py
poliduckie_segmentation/segmentation.py
poliduckie_segmentation/BirdEyeCalibration/BirdEyeMatrix.pkl
poliduckie_segmentation/models/robot_model.casadi
poliduckie_segmentation/models/mpc_model/MPC_N10.casadi
poliduckie_segmentation/models/mpc_model/MPC_N2.casadi
poliduckie_segmentation/models/multiclass_segmentation_model/fingerprint.pb
poliduckie_segmentation/models/multiclass_segmentation_model/keras_metadata.pb
poliduckie_segmentation/models/multiclass_segmentation_model/saved_model.pb
poliduckie_segmentation/models/multiclass_segmentation_model/variables/variables.data-00000-of-00001
poliduckie_segmentation/models/multiclass_segmentation_model/variables/variables.index
poliduckie_segmentation-0.1.17.1.dist-info/LICENSE
poliduckie_segmentation-0.1.17.1.dist-info/METADATA
poliduckie_segmentation-0.1.17.1.dist-info/WHEEL
poliduckie_segmentation-0.1.17.1.dist-info/top_level.txt
poliduckie_segmentation-0.1.17.1.dist-info/RECORD
