Metadata-Version: 2.1
Name: poliduckie-segmentation
Version: 0.1.17.1
Summary: Segmentation from the Poliduckie team.
Home-page: https://github.com/poliduckie/poliduckie_segmentation
Author: Poliduckies
Author-email: duckietown@aeapolimi.it
License: MIT
Keywords: segmentation,duckietown,tensorflow
Platform: UNKNOWN
Classifier: Development Status :: 3 - Alpha
Classifier: Intended Audience :: Developers
Classifier: Topic :: Software Development :: Build Tools
Classifier: License :: OSI Approved :: MIT License
Classifier: Programming Language :: Python :: 3
Requires-Python: >=3.6
License-File: LICENSE
Requires-Dist: casadi
Requires-Dist: numpy
Requires-Dist: opencv-python
Requires-Dist: tensorflow
